dragonfly_uwg/__init__.py
dragonfly_uwg/__main__.py
dragonfly_uwg/_extend_dragonfly.py
dragonfly_uwg/run.py
dragonfly_uwg/terrain.py
dragonfly_uwg/traffic.py
dragonfly_uwg/writer.py
dragonfly_uwg/cli/__init__.py
dragonfly_uwg/cli/simulate.py
dragonfly_uwg/properties/__init__.py
dragonfly_uwg/properties/_refdefaults.py
dragonfly_uwg/properties/building.py
dragonfly_uwg/properties/context.py
dragonfly_uwg/properties/model.py
dragonfly_uwg/properties/room2d.py
dragonfly_uwg/properties/story.py
dragonfly_uwg/simulation/__init__.py
dragonfly_uwg/simulation/boundary.py
dragonfly_uwg/simulation/parameter.py
dragonfly_uwg/simulation/refsite.py
dragonfly_uwg/simulation/runperiod.py
dragonfly_uwg/simulation/vegetation.py
dragonfly_uwg-0.5.743.dist-info/licenses/LICENSE
tests/fixtures/__init__.py
tests/fixtures/boundary.py
tests/fixtures/building.py
tests/fixtures/context.py
tests/fixtures/model.py
tests/fixtures/refsite.py
tests/fixtures/sim_par.py
tests/fixtures/terrain.py
tests/fixtures/traffic.py
tests/fixtures/vegetation.py
dragonfly_uwg-0.5.743.dist-info/METADATA
dragonfly_uwg-0.5.743.dist-info/WHEEL
dragonfly_uwg-0.5.743.dist-info/entry_points.txt
dragonfly_uwg-0.5.743.dist-info/top_level.txt
dragonfly_uwg-0.5.743.dist-info/RECORD
