Metadata-Version: 2.4
Name: dragonfly-uwg
Version: 0.5.743
Summary: Dragonfly extension for the Urban Weather Generator (UWG).
Home-page: https://github.com/ladybug-tools/dragonfly-uwg
Author: Ladybug Tools
Author-email: info@ladybug.tools
License: AGPL-3.0
Classifier: Programming Language :: Python :: 2.7
Classifier: Programming Language :: Python :: 3.7
Classifier: Programming Language :: Python :: 3.8
Classifier: Programming Language :: Python :: 3.9
Classifier: Programming Language :: Python :: 3.10
Classifier: Programming Language :: Python :: 3.11
Classifier: Programming Language :: Python :: 3.12
Classifier: Programming Language :: Python :: Implementation :: CPython
Classifier: Programming Language :: Python :: Implementation :: IronPython
Classifier: Operating System :: OS Independent
License-File: LICENSE
Requires-Dist: dragonfly-core>=1.67.11
Requires-Dist: uwg==5.8.13
Dynamic: author
Dynamic: author-email
Dynamic: classifier
Dynamic: description
Dynamic: description-content-type
Dynamic: home-page
Dynamic: license
Dynamic: license-file
Dynamic: requires-dist
Dynamic: summary
